Workbook

Sheet INSTRUCOES
A1: Grupos de fonte — Saneamento MAPPs
A3: Aba GRUPOS: uma linha por grupo. CÓDIGO é definido por você (curto, sem repetir, ex.: TES). DESCRIÇÃO é o nome exibido no filtro (ex.: Tesouro Estadual).
A4: Aba FONTES: uma linha por fonte, já preenchida com as fontes da base. Informe em GRUPO o CÓDIGO do grupo da fonte (lista de escolha).
A5: Cada fonte pertence a um único grupo. Fonte sem GRUPO fica em "(sem grupo)" no filtro.
A6: CÓDIGO da fonte: os números da fonte na base (ex.: 500-501 para "(500)-(501) Tesouro"). Não altere as colunas CÓDIGO e FONTE NA BASE.
A7: Não renomeie as abas nem os cabeçalhos. O sistema critica o arquivo ao recebê-lo: com erro, ele é recusado e a lista mostra o que corrigir.
A8: Envio: Configurações › Grupos de fonte (versão completa) ou “Carregar grupos de fonte” junto do filtro (versão simplificada).

Sheet GRUPOS
A1: CÓDIGO | B1: DESCRIÇÃO

Sheet FONTES
A1: CÓDIGO | B1: DESCRIÇÃO | C1: GRUPO | D1: FONTE NA BASE | E1: GRUPO
A2: 000-018 | B2: FDS | D2: (000)-(018) FDS | E2: =IF(ISERROR(MATCH(D2, Planilha1!A:A, 0)), "OUTRAS FONTES", "FONTES COGERF") -> OUTRAS FONTES
A3: 000-019 | B3: FEMA | D3: (000)-(019) FEMA | E3: =IF(ISERROR(MATCH(D3, Planilha1!A:A, 0)), "OUTRAS FONTES", "FONTES COGERF") -> OUTRAS FONTES
A4: 000-021 | B4: Governo Municipal - Aplicação Direta | D4: (000)-(021) Governo Municipal - Aplicação Direta | E4: =IF(ISERROR(MATCH(D4, Planilha1!A:A, 0)), "OUTRAS FONTES", "FONTES COGERF") -> OUTRAS FONTES
A5: 000-022 | B5: Governo Federal - Aplicação Direta | D5: (000)-(022) Governo Federal - Aplicação Direta | E5: =IF(ISERROR(MATCH(D5, Planilha1!A:A, 0)), "OUTRAS FONTES", "FONTES COGERF") -> OUTRAS FONTES
A6: 000-023 | B6: Orgaos privados - Aplicação Direta | D6: (000)-(023) Orgaos privados - Aplicação Direta | E6: =IF(ISERROR(MATCH(D6, Planilha1!A:A, 0)), "OUTRAS FONTES", "FONTES COGERF") -> OUTRAS FONTES
A7: 000-024 | B7: Orgãos Internacionais - Aplicação Direta | D7: (000)-(024) Orgãos Internacionais - Aplicação Direta | E7: =IF(ISERROR(MATCH(D7, Planilha1!A:A, 0)), "OUTRAS FONTES", "FONTES COGERF") -> OUTRAS FONTES
A8: 000-025 | B8: Plano de Investimento Especial | D8: (000)-(025) Plano de Investimento Especial | E8: =IF(ISERROR(MATCH(D8, Planilha1!A:A, 0)), "OUTRAS FONTES", "FONTES COGERF") -> OUTRAS FONTES
A9: 000-075 | B9: Medida Compensatória Ambiental | D9: (000)-(075) Medida Compensatória Ambiental | E9: =IF(ISERROR(MATCH(D9, Planilha1!A:A, 0)), "OUTRAS FONTES", "FONTES COGERF") -> OUTRAS FONTES
A10: 000-090 | B10: Programa PADH | D10: (000)-(090) Programa PADH | E10: =IF(ISERROR(MATCH(D10, Planilha1!A:A, 0)), "OUTRAS FONTES", "FONTES COGERF") -> OUTRAS FONTES
A11: 000-095 | B11: Aumento de Capital do Tesouro | D11: (000)-(095) Aumento de Capital do Tesouro | E11: =IF(ISERROR(MATCH(D11, Planilha1!A:A, 0)), "OUTRAS FONTES", "FONTES COGERF") -> OUTRAS FONTES
A12: 000-099 | B12: Aplicação direta de outras entidades | D12: (000)-(099) Aplicação direta de outras entidades | E12: =IF(ISERROR(MATCH(D12, Planilha1!A:A, 0)), "OUTRAS FONTES", "FONTES COGERF") -> OUTRAS FONTES
A13: 000-110 | B13: Tesouro - Precatórios | D13: (000)-(110) Tesouro - Precatórios | E13: =IF(ISERROR(MATCH(D13, Planilha1!A:A, 0)), "OUTRAS FONTES", "FONTES COGERF") -> OUTRAS FONTES
... A105: 500-051 | B105: Tesouro - Recursos Convertidos | D105: (501)-(051) Tesouro - Recursos Convertidos | E105: =IF(ISERROR(MATCH(D105, Planilha1!A:A, 0)), "OUTRAS FONTES", "FONTES COGERF") -> FONTES COGERF

Sheet Planilha1
A1: Fontes Cogerf (Delibera Limite Financeiro)
A2: (500)-(501) Tesouro
A3: (501)-(005) Tesouro - Recursos Hídricos
A4: (501)-(006) Tesouro - Dividendos Cagece
A5: (540)-(050) FUNDEB
A6: (599)-(070) Recursos Próprios / Educação
A7: (659)-(070) Recursos Próprios / Saúde
A8: (669)-(070) Recursos Próprios / Assistência Social
A9: (700)-(070) Recursos Próprios
A10: (704)-(044) Royalties
A11: (750)-(011) CIDE
A12: (754)-(147) Crédito Interno - BNDES/Estados
... A34: (501)-(012) Tesouro - Rendimentos De Empréstimos
